vaccinationvsdeath.py
vaccinationvsdeath-0.0.1.dist-info/METADATA
vaccinationvsdeath-0.0.1.dist-info/WHEEL
vaccinationvsdeath-0.0.1.dist-info/entry_points.txt
vaccinationvsdeath-0.0.1.dist-info/top_level.txt
vaccinationvsdeath-0.0.1.dist-info/RECORD
