Metadata-Version: 2.1
Name: vaccinationvsdeath
Version: 0.0.1
Summary: A package for demonstrate the relationship between covid-19 vaccination rates and deaths
Home-page: https://github.com/G-Y3/covid-19-vaccination-vs.-mortality
Author: Guyu Li
Author-email: lgy778866@gmail.com
License: UNKNOWN
Platform: UNKNOWN
Classifier: Programming Language :: Python :: 3
Classifier: License :: OSI Approved :: MIT License
Classifier: Operating System :: OS Independent
Requires-Python: >=3.6
Requires-Dist: matplotlib
Requires-Dist: seaborn
Requires-Dist: numpy
Requires-Dist: pandas
Requires-Dist: wget
